mov_cli_youtube/__init__.py
mov_cli_youtube/pytube.py
mov_cli_youtube/yt_dlp.py
mov_cli_youtube-1.3.9.dist-info/licenses/LICENSE
mov_cli_youtube-1.3.9.dist-info/METADATA
mov_cli_youtube-1.3.9.dist-info/WHEEL
mov_cli_youtube-1.3.9.dist-info/top_level.txt
mov_cli_youtube-1.3.9.dist-info/RECORD
