Metadata-Version: 2.4
Name: mov-cli-youtube
Version: 1.3.9
Summary: A mov-cli v4 plugin for watching youtube.
Author-email: Goldy <goldy@devgoldy.xyz>, Ananas <ananas@ananas.moe>
License: MIT License
Project-URL: GitHub, https://github.com/mov-cli/mov-cli-youtube
Project-URL: BugTracker, https://github.com/mov-cli/mov-cli-youtube/issues
Keywords: amazing mov-cli plugin
Classifier: Operating System :: Microsoft :: Windows :: Windows 11
Classifier: Operating System :: Microsoft :: Windows :: Windows 10
Classifier: Operating System :: POSIX :: Linux
Classifier: License :: OSI Approved :: MIT License
Classifier: Programming Language :: Python :: 3.9
Classifier: Programming Language :: Python :: 3.10
Classifier: Programming Language :: Python :: 3.11
Classifier: Programming Language :: Python :: 3.12
Requires-Python: >=3.8
License-File: LICENSE
Requires-Dist: requests
Requires-Dist: importlib-metadata; python_version < "3.8"
Requires-Dist: pytubefix>=9.3
Requires-Dist: yt-dlp>=2025.6.30
Provides-Extra: dev
Requires-Dist: ruff; extra == "dev"
Requires-Dist: build; extra == "dev"
Dynamic: license-file
